{"data":{"id":2,"number":"20001","customerId":1,"paymentId":5,"dispatchId":9,"partnerId":"","shopId":1,"invoiceAmount":153.85,"invoiceAmountNet":129.29,"invoiceShipping":3.9,"invoiceShippingNet":3.28,"orderTime":"2017-09-07T14:15:44+0200","transactionId":"","comment":"","customerComment":"","internalComment":"","net":0,"taxFree":0,"temporaryId":"","referer":"","clearedDate":null,"trackingCode":"","languageIso":"1","currency":"EUR","currencyFactor":1,"remoteAddress":"91.36.133.94","deviceType":"desktop","details":[{"id":2,"orderId":2,"articleId":2,"taxId":1,"taxRate":19,"statusId":0,"number":"20001","articleNumber":"SW10002","price":149.95,"quantity":1,"articleName":"TITANIUM CARBON GS 120 cm","shipped":0,"shippedGroup":0,"releaseDate":"-0001-11-30T00:00:00+0100","mode":0,"esdArticle":0,"config":"","ean":"","unit":"","packUnit":"Paar","attribute":{"id":2,"orderDetailId":2,"attribute1":"","attribute2":null,"attribute3":null,"attribute4":null,"attribute5":null,"attribute6":null}}],"documents":[],"payment":{"id":5,"name":"prepayment","description":"Vorkasse","template":"prepayment.tpl","class":"prepayment.php","table":"","hide":false,"additionalDescription":"Sie zahlen einfach vorab und erhalten die Ware bequem und g\u00fcnstig bei Zahlungseingang nach Hause geliefert.","debitPercent":0,"surcharge":0,"surchargeString":"","position":1,"active":true,"esdActive":false,"mobileInactive":false,"embedIFrame":"","hideProspect":0,"action":null,"pluginId":null,"source":null,"attribute":null},"paymentStatus":{"id":17,"name":"open","description":"Offen","position":0,"group":"payment","sendMail":0},"orderStatus":{"id":0,"name":"open","description":"Offen","position":1,"group":"state","sendMail":1},"customer":{"number":"20003","id":1,"paymentId":5,"groupKey":"EK","shopId":1,"priceGroupId":null,"encoderName":"bcrypt","hashPassword":"$2y$10$.TqdM5h2qNqtJbzKF7GpP.kUXWL2UOylkgbqKBU6WuOpDladvkGva","active":true,"email":"werner.hahn@vulke.de","firstLogin":"2017-09-07T00:00:00+0200","lastLogin":"2017-09-07T14:15:44+0200","accountMode":1,"confirmationKey":"","sessionId":"10i196b4lm3r1gjdnurkq18j22","newsletter":0,"validation":"","affiliate":0,"paymentPreset":0,"languageId":"1","referer":"","internalComment":"","failedLogins":0,"lockedUntil":null,"salutation":"mr","title":null,"firstname":"Kalli","lastname":"Kr\u00fcger","birthday":null},"paymentInstances":[{"orderId":2,"firstName":"Kalli","lastName":"Kr\u00fcger","address":"Dorfstr. 6","zipCode":"37318","city":"Sch\u00f6nhagen","bankName":null,"bankCode":null,"accountNumber":null,"accountHolder":null,"bic":null,"iban":null,"amount":"153.8500","createdAt":"2017-09-07T00:00:00+0200","id":1}],"billing":{"title":null,"additionalAddressLine1":null,"additionalAddressLine2":null,"id":1,"orderId":2,"customerId":1,"countryId":2,"stateId":null,"company":"","department":"","salutation":"mr","number":"20003","firstName":"Kalli","lastName":"Kr\u00fcger","street":"Dorfstr. 6","zipCode":"37318","city":"Sch\u00f6nhagen","phone":"","vatId":null,"country":{"id":2,"name":"Deutschland","iso":"DE","isoName":"GERMANY","position":1,"description":"","taxFree":0,"taxFreeUstId":0,"taxFreeUstIdChecked":0,"active":true,"iso3":"DEU","displayStateInRegistration":false,"forceStateInRegistration":false,"areaId":1},"state":null,"attribute":{"id":1,"orderBillingId":1,"text1":null,"text2":null,"text3":null,"text4":null,"text5":null,"text6":null}},"shipping":{"title":"","additionalAddressLine1":"","additionalAddressLine2":"","id":1,"orderId":2,"countryId":2,"stateId":null,"customerId":1,"company":"","department":"","salutation":"mr","firstName":"Kalli","lastName":"Kr\u00fcger","street":"Dorfstr. 6","zipCode":"37318","city":"Sch\u00f6nhagen","attribute":{"id":1,"orderShippingId":1,"text1":null,"text2":null,"text3":null,"text4":null,"text5":null,"text6":null},"country":{"id":2,"name":"Deutschland","iso":"DE","isoName":"GERMANY","position":1,"description":"","taxFree":0,"taxFreeUstId":0,"taxFreeUstIdChecked":0,"active":true,"iso3":"DEU","displayStateInRegistration":false,"forceStateInRegistration":false,"areaId":1},"state":null},"shop":{"id":1,"mainId":null,"categoryId":3,"name":"Demoshop","title":null,"position":0,"host":"shopware.vulke.de","basePath":"","baseUrl":null,"hosts":"shopware.vulke.de","secure":false,"alwaysSecure":false,"secureHost":null,"secureBasePath":null,"templateId":23,"default":true,"active":true,"customerScope":false},"dispatch":{"id":9,"name":"Standard Versand","type":0,"description":"","comment":"","active":true,"position":0,"calculation":0,"surchargeCalculation":3,"taxCalculation":0,"shippingFree":null,"multiShopId":null,"customerGroupId":null,"bindShippingFree":0,"bindTimeFrom":null,"bindTimeTo":null,"bindInStock":null,"bindLastStock":0,"bindWeekdayFrom":null,"bindWeekdayTo":null,"bindWeightFrom":null,"bindWeightTo":null,"bindPriceFrom":null,"bindPriceTo":null,"bindSql":null,"statusLink":"","calculationSql":null,"attribute":null},"attribute":{"id":2,"orderId":2,"attribute1":null,"attribute2":null,"attribute3":null,"attribute4":null,"attribute5":null,"attribute6":null},"languageSubShop":{"id":1,"mainId":null,"categoryId":3,"name":"Demoshop","title":null,"position":0,"host":"shopware.vulke.de","basePath":"","baseUrl":null,"hosts":"shopware.vulke.de","secure":false,"alwaysSecure":false,"secureHost":null,"secureBasePath":null,"templateId":23,"default":true,"active":true,"customerScope":false,"locale":{"id":1,"locale":"de_DE","language":"Deutsch","territory":"Deutschland"}},"paymentStatusId":17,"orderStatusId":0},"success":true}
